q2_umap/__init__.py
q2_umap/citations.bib
q2_umap/plugin_setup.py
q2_umap/umap.py
q2_umap/tests/__init__.py
q2_umap/tests/test_umap.py
q2_umap-0.0.1.dist-info/LICENSE
q2_umap-0.0.1.dist-info/METADATA
q2_umap-0.0.1.dist-info/WHEEL
q2_umap-0.0.1.dist-info/entry_points.txt
q2_umap-0.0.1.dist-info/top_level.txt
q2_umap-0.0.1.dist-info/RECORD
